{
    "E_91": "Systemic/Other",
    "E_53": "Musculoskeletal",
    "E_159": "Neurological",
    "E_129": "Dermatological",
    "E_154": "Dermatological",
    "E_155": "Cardiovascular",
    "E_210": "Gastrointestinal",
    "E_140": "Gastrointestinal",
    "E_51": "Gastrointestinal",
    "E_75": "Ear/Nose/Throat",
    "E_89": "Systemic/Other",
    "E_114": "Psychiatric",
    "E_82": "Systemic/Other",
    "E_148": "Gastrointestinal",
    "E_94": "Systemic/Other",
    "E_220": "Respiratory",
    "E_161": "Gastrointestinal",
    "E_179": "Gastrointestinal",
    "E_162": "Systemic/Other",
    "E_173": "Gastrointestinal",
    "E_33": "Musculoskeletal",
    "E_218": "Musculoskeletal",
    "E_93": "Neurological",
    "E_66": "Respiratory",
    "E_163": "Gastrointestinal",
    "E_30": "Gastrointestinal",
    "E_127": "Ear/Nose/Throat",
    "E_181": "Ear/Nose/Throat",
    "E_88": "Systemic/Other",
    "E_43": "Neurological",
    "E_156": "Neurological",
    "E_144": "Musculoskeletal",
    "E_216": "Musculoskeletal",
    "E_201": "Respiratory",
    "E_217": "Respiratory",
    "E_215": "Gastrointestinal",
    "E_64": "Respiratory",
    "E_96": "Systemic/Other",
    "E_16": "Psychiatric",
    "E_50": "Systemic/Other",
    "E_97": "Ear/Nose/Throat",
    "E_9": "Ear/Nose/Throat",
    "E_76": "Neurological",
    "E_102": "Cardiovascular",
    "E_65": "Gastrointestinal",
    "E_74": "Dermatological",
    "E_205": "Musculoskeletal",
    "E_63": "Ear/Nose/Throat",
    "E_128": "Neurological",
    "E_190": "Gastrointestinal",
    "E_39": "Psychiatric",
    "E_212": "Ear/Nose/Throat",
    "E_206": "Dermatological",
    "E_52": "Neurological",
    "E_203": "Respiratory",
    "E_38": "Musculoskeletal",
    "E_172": "Ear/Nose/Throat",
    "E_84": "Musculoskeletal",
    "E_90": "Musculoskeletal",
    "E_211": "Gastrointestinal",
    "E_166": "Gastrointestinal",
    "E_112": "Respiratory",
    "E_178": "Systemic/Other",
    "E_151": "Systemic/Other",
    "E_45": "Respiratory",
    "E_194": "Respiratory",
    "E_83": "Neurological",
    "E_157": "Neurological",
    "E_176": "Neurological",
    "E_42": "Systemic/Other",
    "E_214": "Respiratory",
    "E_150": "Gastrointestinal",
    "E_32": "Gastrointestinal",
    "E_221": "Musculoskeletal",
    "E_202": "Respiratory",
    "E_219": "Systemic/Other",
    "E_196": "Systemic/Other",
    "E_170": "Dermatological",
    "E_77": "Respiratory",
    "E_13": "Systemic/Other",
    "E_14": "Cardiovascular",
    "E_169": "Ear/Nose/Throat",
    "E_177": "Neurological",
    "E_175": "Systemic/Other",
    "E_174": "Systemic/Other",
    "E_145": "Gastrointestinal",
    "E_92": "Dermatological",
    "E_192": "Musculoskeletal",
    "E_188": "Gastrointestinal",
    "E_164": "Cardiovascular",
    "E_193": "Musculoskeletal",
    "E_168": "Ear/Nose/Throat",
    "E_180": "Neurological",
    "E_67": "Respiratory",
    "E_78": "Psychiatric",
    "E_146": "Cardiovascular",
    "E_171": "Psychiatric",
    "E_111": "Psychiatric",
    "E_182": "Ear/Nose/Throat",
    "E_103": "Ear/Nose/Throat",
    "E_23": "Respiratory",
    "E_105": "Cardiovascular",
    "E_108": "Cardiovascular",
    "E_104": "Cardiovascular",
    "E_79": "Cardiovascular",
    "E_71": "Cardiovascular",
    "E_41": "Systemic/Other",
    "E_100": "Systemic/Other",
    "E_69": "Gastrointestinal",
    "E_167": "Gastrointestinal",
    "E_115": "Gastrointestinal",
    "E_70": "Musculoskeletal",
    "E_10": "Musculoskeletal",
    "E_165": "Respiratory",
    "E_8": "Systemic/Other",
    "E_25": "Neurological",
    "E_184": "Cardiovascular",
    "E_185": "Neurological",
    "E_99": "Neurological",
    "E_107": "Cardiovascular",
    "E_226": "Systemic/Other",
    "E_62": "Psychiatric",
    "E_49": "Ear/Nose/Throat",
    "E_95": "Neurological",
    "E_37": "Gastrointestinal",
    "E_153": "Musculoskeletal",
    "E_124": "Respiratory",
    "E_98": "Gastrointestinal",
    "E_116": "Respiratory",
    "E_48": "Systemic/Other",
    "E_2": "Systemic/Other",
    "E_227": "Systemic/Other",
    "E_61": "Psychiatric",
    "E_47": "Gastrointestinal",
    "E_27": "Systemic/Other",
    "E_143": "Musculoskeletal",
    "E_191": "Respiratory",
    "E_208": "Systemic/Other",
    "E_126": "Gastrointestinal",
    "E_189": "Systemic/Other",
    "E_7": "Systemic/Other",
    "E_24": "Gastrointestinal",
    "E_26": "Gastrointestinal",
    "E_113": "Gastrointestinal",
    "E_160": "Systemic/Other",
    "E_28": "Neurological",
    "E_20": "Musculoskeletal",
    "E_80": "Psychiatric",
    "E_40": "Respiratory",
    "E_0": "Respiratory",
    "E_1": "Ear/Nose/Throat",
    "E_34": "Gastrointestinal",
    "E_209": "Systemic/Other",
    "E_139": "Cardiovascular",
    "E_19": "Cardiovascular",
    "E_31": "Respiratory",
    "E_22": "Cardiovascular",
    "E_60": "Psychiatric",
    "E_35": "Musculoskeletal",
    "E_213": "Psychiatric",
    "E_12": "Systemic/Other",
    "E_44": "Dermatological",
    "E_4": "Ear/Nose/Throat",
    "E_81": "Psychiatric",
    "E_109": "Cardiovascular",
    "E_110": "Musculoskeletal",
    "E_17": "Systemic/Other",
    "E_18": "Gastrointestinal",
    "E_118": "Respiratory",
    "E_123": "Respiratory",
    "E_207": "Systemic/Other",
    "E_86": "Dermatological",
    "E_87": "Respiratory",
    "E_141": "Systemic/Other",
    "E_11": "Systemic/Other",
    "E_186": "Respiratory",
    "E_106": "Cardiovascular",
    "E_158": "Systemic/Other",
    "E_187": "Systemic/Other",
    "E_6": "Gastrointestinal",
    "E_125": "Gastrointestinal",
    "E_21": "Respiratory",
    "E_222": "Respiratory",
    "E_15": "Psychiatric",
    "E_147": "Psychiatric",
    "E_137": "Musculoskeletal",
    "E_149": "Cardiovascular",
    "E_197": "Systemic/Other",
    "E_3": "Cardiovascular",
    "E_29": "Psychiatric",
    "E_225": "Cardiovascular",
    "E_73": "Systemic/Other",
    "E_138": "Musculoskeletal",
    "E_101": "Respiratory",
    "E_46": "Respiratory",
    "E_119": "Ear/Nose/Throat",
    "E_72": "Respiratory",
    "E_198": "Systemic/Other",
    "E_200": "Systemic/Other",
    "E_199": "Systemic/Other",
    "E_121": "Ear/Nose/Throat",
    "E_120": "Ear/Nose/Throat",
    "E_142": "Respiratory",
    "E_195": "Systemic/Other",
    "E_183": "Systemic/Other",
    "E_224": "Respiratory",
    "E_223": "Systemic/Other",
    "E_5": "Respiratory",
    "E_55": "Musculoskeletal",
    "E_57": "Musculoskeletal",
    "E_54": "Musculoskeletal",
    "E_59": "Musculoskeletal",
    "E_56": "Musculoskeletal",
    "E_58": "Musculoskeletal",
    "E_133": "Musculoskeletal",
    "E_130": "Dermatological",
    "E_134": "Musculoskeletal",
    "E_132": "Dermatological",
    "E_136": "Dermatological",
    "E_135": "Dermatological",
    "E_131": "Dermatological",
    "E_152": "Musculoskeletal",
    "E_204": "Systemic/Other"
}